Workbook

Sheet MENU
B3: DESCOMPLICA IR | F3: ORGANIZADOR DE IMPOSTO DE RENDA
B6: NAVEGAÇÃO
F7: VISÃO GERAL DO PREENCHIMENTO
B8: MENU
F9: Titular cadastrado | K9: =IF(TITULAR!I9="","PENDENTE","PREENCHIDO") -> PREENCHIDO
B11: =HYPERLINK("#'TITULAR'!A1","TITULAR") -> TITULAR
F12: Informes registrados | K12: =COUNTIF(INFORMES!F11:F22,"<>") -> 0
B14: =HYPERLINK("#'INFORMES'!A1","INFORMES") -> INFORMES
F15: Notas registradas | K15: =COUNTIF(NOTAS!F11:F45,"<>") -> 0
B17: =HYPERLINK("#'NOTAS'!A1","NOTAS") -> NOTAS
F18: Total de informes | K18: =SUM(INFORMES!I11:I22) -> 8460
F21: Total de notas | K21: =SUM(NOTAS!J11:J45) -> 0
F25: COMO UTILIZAR
F27: 1 | TITULAR — registre os seus dados pessoais.
F29: 2 | INFORMES — registre instituições, rendimentos e saldos.
F31: 3 | NOTAS — registre entradas e saídas com seus comprovantes.
B34: BY DIO • VITORIA

Sheet TITULAR
B3: DESCOMPLICA IR | F3: DADOS DO TITULAR
B6: NAVEGAÇÃO
F7: IDENTIFICAÇÃO DO CONTRIBUINTE
B8: =HYPERLINK("#'MENU'!A1","MENU") -> MENU
F9: Nome completo | I9: MARCIA DE PAULA
B11: =HYPERLINK("#'TITULAR'!A1","TITULAR") -> TITULAR | F11: CPF | I11: 5204804701
F13: Data de nascimento | I13: 31099
B14: =HYPERLINK("#'INFORMES'!A1","INFORMES") -> INFORMES
F15: Título de eleitor | I15: 514110124575415
B17: =HYPERLINK("#'NOTAS'!A1","NOTAS") -> NOTAS | F17: Profissão / ocupação | I17: PROFESSORA
F19: Telefone | I19: 63 945895145
F21: E-mail | I21: marcinhafluflu@gmail.com
F24: ENDEREÇO E INFORMAÇÕES COMPLEMENTARES
F26: Logradouro e número | I26: Rua do sol, 14
F28: Complemento / bairro | I28: Bairra Novo
F30: Cidade / UF | I30: Curitiba
F32: CEP | I32: 6652455
B34: BY DIO • VITORIA | F34: Observações

Sheet INFORMES
B3: DESCOMPLICA IR | F3: INFORMES DE RENDIMENTOS
B6: NAVEGAÇÃO
F7: REGISTRO DE INFORMES E INSTITUIÇÕES FINANCEIRAS
B8: =HYPERLINK("#'MENU'!A1","MENU") -> MENU | F8: Informe um registro por linha. Utilize os valores informados nos documentos oficiais das instituições.
F10: Instituição / fonte | G10: Tipo de informe | H10: Ano-calendário | I10: Valor (R$) | J10: Situação | K10: Recebido?
B11: =HYPERLINK("#'TITULAR'!A1","TITULAR") -> TITULAR | G11: Bancário | H11: 2026 | I11: 8460 | J11: Pendente | K11: Sim
B14: =HYPERLINK("#'INFORMES'!A1","INFORMES") -> INFORMES
B17: =HYPERLINK("#'NOTAS'!A1","NOTAS") -> NOTAS
B21: BY DIO • VITORIA
H24: TOTAL DOS INFORMES | I24: =SUM(I11:I22) -> 8460

Sheet NOTAS
B3: DESCOMPLICA IR | F3: NOTAS E LANÇAMENTOS
F5: Preencha os campos claros e utilize a navegação lateral para alternar entre as etapas.
B6: NAVEGAÇÃO
F7: CONTROLE DE NOTAS E COMPROVANTES
B8: =HYPERLINK("#'MENU'!A1","MENU") -> MENU | F8: Registre recebimentos, despesas e documentos para facilitar a conferência antes da declaração.
F10: Descrição | G10: Data | H10: Categoria | I10: Natureza | J10: Valor (R$) | K10: Conferência
B11: =HYPERLINK("#'TITULAR'!A1","TITULAR") -> TITULAR | G11: 46295 | H11: Outro | I11: Entrada | K11: Pendente
B14: =HYPERLINK("#'INFORMES'!A1","INFORMES") -> INFORMES
B17: =HYPERLINK("#'NOTAS'!A1","NOTAS") -> NOTAS
B34: BY DIO • VITORIA
